{
    "wallpaper": "/home/dingo/Pictures/wallpapers/Dynamic-Wallpapers/Light/Garden-Light.png",
    "alpha": "100",
    "special": {
        "background": "#171815",
        "foreground": "#c8dfe9",
        "cursor": "#c8dfe9"
    },
    "colors": {
        "color0": "#171815",
        "color1": "#4D7293",
        "color2": "#A6718F",
        "color3": "#6794A2",
        "color4": "#78B2D5",
        "color5": "#9DA59C",
        "color6": "#C0C1AF",
        "color7": "#c8dfe9",
        "color8": "#8c9ca3",
        "color9": "#4D7293",
        "color10": "#A6718F",
        "color11": "#6794A2",
        "color12": "#78B2D5",
        "color13": "#9DA59C",
        "color14": "#C0C1AF",
        "color15": "#c8dfe9"
    }
}